typed_pytest/__init__.py
typed_pytest/__init__.pyi
typed_pytest/_factory.py
typed_pytest/_fixtures.py
typed_pytest/_method.py
typed_pytest/_mock.py
typed_pytest/_mocker.py
typed_pytest/_property.py
typed_pytest/_protocols.py
typed_pytest/_version.py
typed_pytest/py.typed
typed_pytest_generator/__init__.py
typed_pytest_generator/_backend.py
typed_pytest_generator/_backend_inspect.py
typed_pytest_generator/_backend_stubgen.py
typed_pytest_generator/_config.py
typed_pytest_generator/_generator.py
typed_pytest_generator/_inspector.py
typed_pytest_generator/_templates.py
typed_pytest_generator/cli.py
typed_pytest_generator/py.typed
typed_pytest-0.1.8.dist-info/METADATA
typed_pytest-0.1.8.dist-info/WHEEL
typed_pytest-0.1.8.dist-info/entry_points.txt
typed_pytest-0.1.8.dist-info/RECORD
