Metadata-Version: 2.4
Name: typed-pytest
Version: 0.1.8
Summary: Type-safe mocking for pytest - preserve original type hints while using mock features
Project-URL: Homepage, https://github.com/tmdgusya/typed-pytest
Project-URL: Documentation, https://github.com/tmdgusya/typed-pytest#readme
Project-URL: Repository, https://github.com/tmdgusya/typed-pytest
Project-URL: Issues, https://github.com/tmdgusya/typed-pytest/issues
Author: typed-pytest contributors
License: MIT
Keywords: mock,pytest,testing,type-hints,typing
Classifier: Development Status :: 3 - Alpha
Classifier: Framework :: Pytest
Classifier: Intended Audience :: Developers
Classifier: License :: OSI Approved :: MIT License
Classifier: Programming Language :: Python :: 3
Classifier: Programming Language :: Python :: 3.10
Classifier: Programming Language :: Python :: 3.11
Classifier: Programming Language :: Python :: 3.12
Classifier: Programming Language :: Python :: 3.13
Classifier: Topic :: Software Development :: Testing
Classifier: Topic :: Software Development :: Testing :: Mocking
Classifier: Typing :: Typed
Requires-Python: >=3.10
Requires-Dist: pytest-mock>=3.11
Requires-Dist: pytest>=8.0
Requires-Dist: tomli>=2.0; python_version < '3.11'
Provides-Extra: dev
Requires-Dist: mypy>=1.8; extra == 'dev'
Requires-Dist: pre-commit>=3.6; extra == 'dev'
Requires-Dist: pyright>=1.1.350; extra == 'dev'
Requires-Dist: pytest-asyncio>=0.23; extra == 'dev'
Requires-Dist: pytest-cov>=4.1; extra == 'dev'
Requires-Dist: ruff>=0.4.0; extra == 'dev'
Requires-Dist: types-mock>=5.0; extra == 'dev'
